bitmap_fonts/__init__.py
bitmap_fonts/create_font_texture.py
bitmap_fonts-0.3.1.dist-info/entry_points.txt
bitmap_fonts-0.3.1.dist-info/WHEEL
bitmap_fonts-0.3.1.dist-info/METADATA
bitmap_fonts-0.3.1.dist-info/RECORD
