Metadata-Version: 2.1
Name: bitmap-fonts
Version: 0.3.1
Summary: Creation of bitmap fonts useful in OpenGL context.
Home-page: https://www.simuneatomistics.com/
License: MIT
Keywords: Bitmap fonts,OpenGL,textures
Author: Simune Team
Author-email: devops@simuneatomistics.com
Requires-Python: >=3.8,<3.10
Classifier: Development Status :: 3 - Alpha
Classifier: License :: OSI Approved :: MIT License
Classifier: Operating System :: OS Independent
Classifier: Programming Language :: Python :: 3
Classifier: Programming Language :: Python :: 3 :: Only
Classifier: Programming Language :: Python :: 3.8
Classifier: Programming Language :: Python :: 3.9
Requires-Dist: click (>=7.0.0,<9.0.0)
Requires-Dist: pillow (>=9.1.0,<10.0.0)
Project-URL: Repository, https://gitlab.com/simune/components/bitmap-fonts
